isa_mcp/__init__.py
isa_mcp/mcp_client.py
isa_mcp-1.0.0.dist-info/licenses/LICENSE
isa_mcp-1.0.0.dist-info/METADATA
isa_mcp-1.0.0.dist-info/WHEEL
isa_mcp-1.0.0.dist-info/top_level.txt
isa_mcp-1.0.0.dist-info/RECORD
