Metadata-Version: 2.4
Name: isa-mcp
Version: 1.0.0
Summary: isA MCP Client - Python client library for interacting with MCP (Model Context Protocol) servers
Author-email: ISA Team <info@isa-mcp.com>
License: MIT
Project-URL: Homepage, https://github.com/isa-agent/mcp
Project-URL: Repository, https://github.com/isa-agent/mcp
Keywords: mcp,client,ai,llm,tools
Classifier: Development Status :: 4 - Beta
Classifier: Intended Audience :: Developers
Classifier: Topic :: Software Development :: Libraries :: Python Modules
Classifier: Programming Language :: Python :: 3
Classifier: Programming Language :: Python :: 3.10
Classifier: Programming Language :: Python :: 3.11
Classifier: Programming Language :: Python :: 3.12
Requires-Python: >=3.10
License-File: LICENSE
Requires-Dist: aiohttp>=3.9.0
Requires-Dist: httpx>=0.26.0
Provides-Extra: dev
Requires-Dist: pytest>=7.0.0; extra == "dev"
Requires-Dist: black>=23.0.0; extra == "dev"
Requires-Dist: mypy>=1.0.0; extra == "dev"
Dynamic: license-file
